{"Id":525,"Name":"Illusionist\u0027s Bracers","PageContent":"\n\nSource: Guildmaster\u0027s Guide to Ravnica\nWondrous item, very rare (requires attunement by a spellcaster)\nA powerful illusionist of House Dimir originally developed these bracers. which enabled her to create multiple minor illusions at once. The bracers\u0027 power, though, extends far beyond illusions.\nWhile wearing the bracers. whenever you cast a cantrip, you can use a bonus action on the same turn to cast that cantrip a second time.\n\n\n\n\n","Source":"Guildmaster\u0027s Guide to Ravnica","Type":"wondrous item","Rarity":"very rare","RequiresAttunment":true}