{"Id":265,"Name":"Revivify","School":"necromancy","Level":3,"PageContent":"Source: Player\u0027s Handbook\n3rd-level necromancy\nCasting Time: 1 action\nRange: Touch\nComponents: V, S, M (diamonds worth 300 gp, which the spell consumes)\nDuration: Instantaneous\nYou touch a creature that has died within the last minute. That creature returns to life with 1 hit point. This spell can\u2019t return to life a creature that has died of old age, nor can it restore any missing body parts.\nSpell Lists. Artificer, Cleric, Druid (Optional), Paladin, Ranger (Optional)","InLists":["Artificer","Cleric","Druid (Optional)","Paladin","Ranger (Optional)"],"Source":"Player\u0027s Handbook","CastingTime":"1 action","Components":["V","S","M (diamonds worth 300 gp","which the spell consumes)"],"Range":"touch","Duration":"instantaneous","WikidotLink":"http://dnd5e.wikidot.com//spell:revivify"}