{"Id":479,"Name":"Abi-Dalzim\u0027s Horrid Wilting","School":"necromancy","Level":8,"PageContent":"Source: Xanathar\u0027s Guide to Everything\n8th-level necromancy\nCasting Time: 1 action\nRange: 150 feet\nComponents: V, S, M (a bit of sponge)\nDuration: Instantaneous\nYou draw the moisture from every creature in a 30-foot cube centered on a point you choose within range. Each creature in that area must make a Constitution saving throw. Constructs and undead aren\u2019t affected, and plants and water elementals make this saving throw with disadvantage. A creature takes 10d8 necrotic damage on a failed save, or half as much damage on a successful one.\nSpell Lists. Sorcerer, Wizard","InLists":["Sorcerer","Wizard"],"Source":"Xanathar\u0027s Guide to Everything","CastingTime":"1 action","Components":["V","S","M (a bit of sponge)"],"Range":"150 feet","Duration":"instantaneous"}